{
  "report_id": "coverage_report_1763701395",
  "report_name": "接口场景覆盖度评分报告",
  "generated_time": "2025-11-21 13:03:18",
  "summary": {
    "overall_coverage": 0.0,
    "overall_level": "poor",
    "total_scenarios": 3,
    "coverage_by_type": {
      "functional": 0.0,
      "parameter": 0.0,
      "exception": 0.0,
      "business": 0.0,
      "integration": 0.0
    },
    "coverage_by_tag": {
      "authentication": 0.0,
      "user": 0.0,
      "e-commerce": 0.0,
      "shopping": 0.0,
      "order": 0.0
    }
  },
  "recommendations": [
    "整体功能测试覆盖度较低(0.0%)，建议重点加强这方面的测试",
    "场景'用户注册登录场景'覆盖度最低(0.0%)，建议优先改进",
    "整体测试覆盖度较低，建议全面审查测试策略，增加测试用例"
  ],
  "scenarios": [
    {
      "scenario_id": "user_auth_scenario",
      "scenario_name": "用户注册登录场景",
      "description": "用户注册、登录、获取个人信息的完整流程",
      "api_endpoints": [
        "/api/auth/register",
        "/api/auth/login",
        "/api/user/profile"
      ],
      "tags": [
        "authentication",
        "user"
      ],
      "priority": "high",
      "business_value": "high",
      "coverage": {
        "total_coverage": 0.0,
        "coverage_level": "poor",
        "coverage_by_type": {
          "functional": 0.0,
          "parameter": 0.0,
          "exception": 0.0,
          "business": 0.0,
          "integration": 0.0
        },
        "test_cases": [],
        "missing_tests": [
          "功能测试覆盖不足，需要增加对核心功能的测试用例",
          "参数测试覆盖不足，需要增加对参数边界值和异常值的测试用例",
          "异常测试覆盖不足，需要增加对各种异常情况的测试用例",
          "业务场景测试覆盖不足，需要增加对完整业务流程的测试用例",
          "集成测试覆盖不足，需要增加对API间交互的测试用例"
        ],
        "recommendations": [
          "建议为场景'用户注册登录场景'添加更多功能测试用例，确保所有核心功能都被覆盖",
          "建议为场景'用户注册登录场景'添加参数测试用例，包括边界值、空值和异常值",
          "建议为场景'用户注册登录场景'添加异常处理测试用例，验证系统在异常情况下的行为",
          "建议为场景'用户注册登录场景'添加端到端业务流程测试，验证完整的业务流程",
          "建议为场景'用户注册登录场景'添加API集成测试，验证不同API之间的交互",
          "场景'用户注册登录场景'是高优先级场景，建议提高其测试覆盖度至80%以上",
          "场景'用户注册登录场景'具有高业务价值，建议提高其测试覆盖度至80%以上"
        ]
      }
    },
    {
      "scenario_id": "shopping_scenario",
      "scenario_name": "商品浏览购买场景",
      "description": "用户浏览商品、添加购物车、创建订单的完整流程",
      "api_endpoints": [
        "/api/products",
        "/api/products/{product_id}",
        "/api/cart",
        "/api/orders"
      ],
      "tags": [
        "e-commerce",
        "shopping"
      ],
      "priority": "high",
      "business_value": "high",
      "coverage": {
        "total_coverage": 0.0,
        "coverage_level": "poor",
        "coverage_by_type": {
          "functional": 0.0,
          "parameter": 0.0,
          "exception": 0.0,
          "business": 0.0,
          "integration": 0.0
        },
        "test_cases": [],
        "missing_tests": [
          "功能测试覆盖不足，需要增加对核心功能的测试用例",
          "参数测试覆盖不足，需要增加对参数边界值和异常值的测试用例",
          "异常测试覆盖不足，需要增加对各种异常情况的测试用例",
          "业务场景测试覆盖不足，需要增加对完整业务流程的测试用例",
          "集成测试覆盖不足，需要增加对API间交互的测试用例"
        ],
        "recommendations": [
          "建议为场景'商品浏览购买场景'添加更多功能测试用例，确保所有核心功能都被覆盖",
          "建议为场景'商品浏览购买场景'添加参数测试用例，包括边界值、空值和异常值",
          "建议为场景'商品浏览购买场景'添加异常处理测试用例，验证系统在异常情况下的行为",
          "建议为场景'商品浏览购买场景'添加端到端业务流程测试，验证完整的业务流程",
          "建议为场景'商品浏览购买场景'添加API集成测试，验证不同API之间的交互",
          "场景'商品浏览购买场景'是高优先级场景，建议提高其测试覆盖度至80%以上",
          "场景'商品浏览购买场景'具有高业务价值，建议提高其测试覆盖度至80%以上"
        ]
      }
    },
    {
      "scenario_id": "order_management_scenario",
      "scenario_name": "订单管理场景",
      "description": "用户查看订单、取消订单的流程",
      "api_endpoints": [
        "/api/orders",
        "/api/orders/{order_id}/cancel"
      ],
      "tags": [
        "e-commerce",
        "order"
      ],
      "priority": "medium",
      "business_value": "medium",
      "coverage": {
        "total_coverage": 0.0,
        "coverage_level": "poor",
        "coverage_by_type": {
          "functional": 0.0,
          "parameter": 0.0,
          "exception": 0.0,
          "business": 0.0,
          "integration": 0.0
        },
        "test_cases": [],
        "missing_tests": [
          "功能测试覆盖不足，需要增加对核心功能的测试用例",
          "参数测试覆盖不足，需要增加对参数边界值和异常值的测试用例",
          "异常测试覆盖不足，需要增加对各种异常情况的测试用例",
          "业务场景测试覆盖不足，需要增加对完整业务流程的测试用例",
          "集成测试覆盖不足，需要增加对API间交互的测试用例"
        ],
        "recommendations": [
          "建议为场景'订单管理场景'添加更多功能测试用例，确保所有核心功能都被覆盖",
          "建议为场景'订单管理场景'添加参数测试用例，包括边界值、空值和异常值",
          "建议为场景'订单管理场景'添加异常处理测试用例，验证系统在异常情况下的行为",
          "建议为场景'订单管理场景'添加端到端业务流程测试，验证完整的业务流程",
          "建议为场景'订单管理场景'添加API集成测试，验证不同API之间的交互"
        ]
      }
    }
  ]
}